strawberry_django_dataloaders/__init__.py
strawberry_django_dataloaders/core/__init__.py
strawberry_django_dataloaders/core/dataloader.py
strawberry_django_dataloaders/core/factory.py
strawberry_django_dataloaders/dataloaders.py
strawberry_django_dataloaders/exceptions.py
strawberry_django_dataloaders/factories.py
strawberry_django_dataloaders/fields.py
strawberry_django_dataloaders/views.py
strawberry_django_dataloaders-0.2.0.dist-info/LICENSE.md
strawberry_django_dataloaders-0.2.0.dist-info/METADATA
strawberry_django_dataloaders-0.2.0.dist-info/WHEEL
strawberry_django_dataloaders-0.2.0.dist-info/RECORD
