Metadata-Version: 2.1
Name: strawberry-django-dataloaders
Version: 0.2.0
Summary: A set of tools for using dataloaders with Django and Strawberry GraphQL.
Home-page: https://github.com/VojtechPetru/strawberry-django-dataloaders
License: LICENSE.md
Keywords: strawberry,django,graphql,dataloader
Author: vojtech
Author-email: petru.vojtech@gmail.com
Requires-Python: >=3.10,<4.0
Classifier: License :: Other/Proprietary License
Classifier: Programming Language :: Python :: 3
Classifier: Programming Language :: Python :: 3.10
Classifier: Programming Language :: Python :: 3.11
Classifier: Programming Language :: Python :: 3.12
Requires-Dist: Django (>=3.2)
Requires-Dist: strawberry-graphql-django (>=0.9)
Project-URL: Repository, https://github.com/VojtechPetru/strawberry-django-dataloaders
